[{"name":"14th St","description":"Cillum velit amet occaecat velit commodo velit irure ea quis nostrud. Qui cillum nisi nisi labore in amet veniam fugiat reprehenderit et magna ullamco. Eiusmod mollit ea est minim veniam Lorem occaecat ad. Aliqua nisi culpa nisi esse Lorem dolor pariatur laborum sunt. Cillum deserunt consequat excepteur ut irure consequat id est et elit sint.","grade":7,"distance":0.85,"lane_type":"Dedicated Lane","geojson":{"type":"Feature","properties":{"name":"14th St"},"geometry":{"coordinates":[[-122.431125,37.767593],[-122.415676,37.76856]],"type":"LineString"},"id":"fe1e40fc5785fbae6eec6dfc53268ac2","centroid":[-122.4234005,37.7680765]}},{"name":"Great Highway","description":"Dolor irure ipsum do dolore labore aliquip minim. Voluptate aliqua officia veniam aute elit mollit. Laboris ex est deserunt labore irure Lorem nostrud duis incididunt pariatur quis. Est nostrud esse sunt non incididunt ad. Veniam qui aliquip laborum occaecat nulla minim occaecat mollit ut laboris exercitation magna ipsum.","grade":3,"distance":3.02,"lane_type":"Bike Path","geojson":{"type":"Feature","properties":{"name":"Great Highway"},"geometry":{"coordinates":[[-122.513641,37.778533],[-122.511441,37.776065],[-122.511312,37.774098],[-122.511377,37.772733],[-122.510411,37.766202],[-122.510411,37.763912],[-122.508201,37.747507],[-122.506871,37.73658],[-122.506817,37.735587]],"type":"LineString"},"id":"f442fb9acd262bb7a3e64908e0f1f33f","centroid":[-122.51005355555556,37.76124633333333]}},{"name":"Taraval Street","description":"Nostrud labore velit mollit dolore dolor mollit sit tempor eiusmod adipisicing qui. Dolor ipsum irure anim officia eu laborum ullamco velit est anim excepteur irure exercitation. Voluptate aliquip sit aliqua fugiat mollit elit sit enim amet. Commodo enim enim quis voluptate occaecat incididunt est nostrud Lorem culpa ipsum culpa. Dolor enim commodo deserunt aliqua.","grade":8,"distance":1.53,"lane_type":"Sharrows","geojson":{"type":"Feature","properties":{"name":"Taraval Street"},"geometry":{"coordinates":[[-122.491829,37.742366],[-122.470114,37.743333],[-122.463891,37.743757]],"type":"LineString"},"id":"f23f1af915423cc5b770406049d4ca3c","centroid":[-122.475278,37.743152]}},{"name":"Arguello","description":"Laborum voluptate laboris ipsum occaecat cupidatat voluptate laborum non exercitation. Est Lorem consequat enim enim ipsum duis nostrud. Incididunt duis fugiat do fugiat duis sunt sunt voluptate esse voluptate sit enim. Enim proident magna nulla Lorem. Reprehenderit et est Lorem duis reprehenderit laborum cillum minim velit ad nulla minim ad do.","grade":4,"distance":1.42,"lane_type":"Sharrows","geojson":{"type":"Feature","properties":{"name":"Arguello"},"geometry":{"coordinates":[[-122.458355,37.77414],[-122.459471,37.789675],[-122.45872,37.79015],[-122.458891,37.790964],[-122.458891,37.792066],[-122.459878,37.79249],[-122.460694,37.792575],[-122.461466,37.793066]],"type":"LineString"},"id":"d5342adb306fed6fdaebdd9c0c430009","centroid":[-122.45954574999999,37.78939075]}},{"name":"JFK Drive","description":"Esse dolore minim consectetur magna cillum eiusmod sunt fugiat eu nisi dolor tempor sunt incididunt. Est eiusmod quis irure aliquip labore mollit laborum deserunt qui dolore exercitation ut fugiat veniam. Laboris eiusmod elit enim excepteur nostrud qui commodo mollit quis aute nisi officia. Reprehenderit laboris adipisicing proident elit id consequat cupidatat sit officia. Excepteur duis et consectetur qui.","grade":0,"distance":3.42,"lane_type":"Bike Path","geojson":{"type":"Feature","properties":{"name":"JFK Drive"},"geometry":{"coordinates":[[-122.454045,37.771499],[-122.455093,37.771062],[-122.455509,37.77095],[-122.456306,37.770928],[-122.459699,37.771405],[-122.462067,37.771783],[-122.46491,37.772508],[-122.465881,37.772614],[-122.468242,37.772512],[-122.468751,37.772427],[-122.469266,37.772224],[-122.469593,37.772046],[-122.471203,37.770969],[-122.471712,37.770782],[-122.472104,37.770714],[-122.472469,37.770765],[-122.47477,37.771558],[-122.475178,37.771681],[-122.475526,37.771719],[-122.475988,37.771681],[-122.476707,37.771567],[-122.477908,37.771282],[-122.480065,37.77043],[-122.481379,37.770036],[-122.481985,37.770019],[-122.482409,37.770023],[-122.483482,37.770205],[-122.483702,37.770193],[-122.484598,37.769998],[-122.484973,37.769998],[-122.485284,37.770082],[-122.486711,37.770799],[-122.487146,37.77088],[-122.487591,37.770846],[-122.488589,37.770748],[-122.490429,37.770939],[-122.491287,37.770909],[-122.492215,37.770748],[-122.494103,37.770142],[-122.49471,37.770201],[-122.495166,37.770057],[-122.495756,37.769497],[-122.496255,37.769294],[-122.498084,37.768908],[-122.501721,37.767759],[-122.506238,37.766686],[-122.506721,37.767025],[-122.507187,37.76781],[-122.507885,37.768819],[-122.508523,37.769421],[-122.509505,37.77004],[-122.510443,37.770388],[-122.511034,37.770443]],"type":"LineString"},"id":"d4d939041c46ec845377b23574fe2072","centroid":[-122.48317175471698,37.77052866037735]}},{"name":"Golden Gate Bridge","description":"Ut laborum consectetur in aute ipsum est cupidatat amet cillum do aute. Dolor aute proident officia do veniam mollit anim reprehenderit aliquip pariatur minim officia reprehenderit. Sit tempor sint eu tempor elit. Nisi Lorem sint ea Lorem est sunt labore sit duis tempor ullamco et aliqua reprehenderit. Qui aliquip ullamco est officia anim.","grade":5,"distance":1.8,"lane_type":"Bike Path","geojson":{"type":"Feature","properties":{"name":"Golden Gate Bridge"},"geometry":{"coordinates":[[-122.476615,37.807957],[-122.477238,37.808766],[-122.477479,37.809351],[-122.477543,37.809885],[-122.479984,37.830649],[-122.480306,37.831547],[-122.480918,37.832259],[-122.481256,37.832433],[-122.481591,37.83249],[-122.482326,37.832831]],"type":"LineString"},"id":"ccbc782656fec979775fc4a60186fb3f","centroid":[-122.47952560000002,37.8228168]}},{"name":"2nd St","description":"Cillum dolore adipisicing exercitation dolore fugiat. Ut nisi enim sint cupidatat non officia enim tempor nostrud ad laboris do. Adipisicing ipsum irure sint in esse reprehenderit non labore Lorem. Pariatur proident aute adipisicing proident mollit incididunt. Velit ex magna magna laboris cupidatat sunt.","grade":6,"distance":0.92,"lane_type":"Separated Lane","geojson":{"type":"Feature","properties":{"name":"2nd St"},"geometry":{"coordinates":[[-122.389562,37.779839],[-122.401428,37.789268]],"type":"LineString"},"id":"be187bc3137b5063665ea482c5259219","centroid":[-122.395495,37.7845535]}},{"name":"17th Street","description":"Voluptate esse ea enim deserunt. Sunt commodo in sit anim aute cillum. Qui ullamco eiusmod esse esse aliquip irure magna occaecat aliquip. Velit et commodo sint in minim dolore in laborum aliquip. Ad proident aliquip labore minim minim eu.","grade":4,"distance":2.38,"lane_type":"Bike Path","geojson":{"type":"Feature","properties":{"name":"17th Street"},"geometry":{"coordinates":[[-122.43076,37.762742],[-122.413659,37.763794],[-122.412908,37.764201],[-122.407414,37.764489],[-122.394862,37.765218],[-122.394948,37.766372],[-122.394604,37.766626],[-122.38909,37.766898]],"type":"LineString"},"id":"bc691a9b6cdba681e7a32c9d3df68a0f","centroid":[-122.404780625,37.76504249999999]}},{"name":"8th Avenue","description":"Velit aliqua do nisi incididunt occaecat excepteur officia. Ea esse excepteur aliqua est velit consectetur tempor veniam enim Lorem. In quis laboris aute esse duis esse nulla laborum. Irure ipsum occaecat est laborum tempor cupidatat qui incididunt in Lorem commodo est. Mollit anim id ipsum ullamco veniam.","grade":7,"distance":0.96,"lane_type":"Bike Path","geojson":{"type":"Feature","properties":{"name":"8th Avenue"},"geometry":{"coordinates":[[-122.466788,37.786555],[-122.465887,37.772614]],"type":"LineString"},"id":"b93fa0930bf0f490fbf57f54e7f9703e","centroid":[-122.4663375,37.7795845]}},{"name":"25th Ave","description":"Consequat labore id irure culpa sunt nostrud et tempor reprehenderit et. Commodo consectetur proident sint aute velit do officia ea. Adipisicing nulla officia exercitation adipisicing exercitation sit consectetur dolore commodo amet laboris laborum amet. Esse cupidatat eiusmod sint aliqua. Id laborum nostrud elit enim sint ullamco et eiusmod esse.","grade":3,"distance":1.06,"lane_type":"Separated Lane","geojson":{"type":"Feature","properties":{"name":"25th Ave"},"geometry":{"coordinates":[[-122.485306,37.787623],[-122.484211,37.772326]],"type":"LineString"},"id":"b7d612afeec288b77c7881c0a0b47621","centroid":[-122.4847585,37.7799745]}},{"name":"Valencia Street","description":"Culpa sint sit nostrud voluptate est nisi nulla id nulla eiusmod elit laborum. Labore ex commodo occaecat incididunt. Nostrud ut mollit ipsum Lorem minim cupidatat deserunt nisi. Ex ea reprehenderit aliquip et amet ut ad eu occaecat eiusmod dolor ex eu. Duis incididunt ipsum est ad consectetur.","grade":3,"distance":1.81,"lane_type":"Shared Lane","geojson":{"type":"Feature","properties":{"name":"Valencia Street"},"geometry":{"coordinates":[[-122.422649,37.77258],[-122.420139,37.746481]],"type":"LineString"},"id":"b1871ed684b974d6f3a6b9993279f0d0","centroid":[-122.421394,37.7595305]}},{"name":"Polk Street","description":"Exercitation incididunt id sint proident in cupidatat. Eiusmod qui anim minim eiusmod nulla laborum aliqua nulla consectetur dolore. Velit quis non officia aliquip ad nostrud aliqua et ad. Est excepteur nostrud enim ut consectetur cupidatat anim anim. Cupidatat fugiat eiusmod irure quis anim excepteur quis mollit.","grade":6,"distance":2.09,"lane_type":"Dedicated Lane","geojson":{"type":"Feature","properties":{"name":"Polk Street"},"geometry":{"coordinates":[[-122.4175,37.776578],[-122.41787,37.776829],[-122.418556,37.780242],[-122.42384,37.80624]],"type":"LineString"},"id":"9b16b7d06ef9675a1620a42a2a4e223c","centroid":[-122.41944149999999,37.784972249999996]}},{"name":"Marina Blvd","description":"Ullamco sunt qui est ullamco id nulla duis minim velit minim tempor consequat duis id. Tempor duis eiusmod id nostrud dolor quis ipsum eu. Ipsum id amet cupidatat veniam mollit quis officia qui nulla. Aliqua mollit Lorem officia veniam anim occaecat sit eiusmod cupidatat ut laborum dolor nisi. Nulla quis proident consectetur incididunt do nulla ex proident incididunt.","grade":4,"distance":0.93,"lane_type":"Dedicated Lane","geojson":{"type":"Feature","properties":{"name":"Marina Blvd"},"geometry":{"coordinates":[[-122.448291,37.805037],[-122.436318,37.806562],[-122.433786,37.805003],[-122.432155,37.805206]],"type":"LineString"},"id":"994f24657d421076c855c65324dce58d","centroid":[-122.4376375,37.805452]}},{"name":"Sloat Boulevard","description":"Veniam nisi enim officia mollit dolore ad exercitation. Aute officia eiusmod irure ea consectetur. Culpa dolor dolore qui minim aliquip ex cillum minim dolore sunt qui irure ea. Laboris consequat elit cupidatat eu dolor est. Ut incididunt amet ad consectetur esse culpa occaecat deserunt.","grade":9,"distance":1.94,"lane_type":"Dedicated Lane","geojson":{"type":"Feature","properties":{"name":"Sloat Boulevard"},"geometry":{"coordinates":[[-122.506613,37.735494],[-122.501635,37.735358],[-122.499403,37.734407],[-122.495884,37.733797],[-122.471551,37.734849]],"type":"LineString"},"id":"9336f3d22e09f5b5674259f8a13283ed","centroid":[-122.4950172,37.734781000000005]}},{"name":"Kirkham St","description":"Magna do deserunt ea velit laboris velit culpa commodo nisi ullamco Lorem exercitation. Consectetur officia reprehenderit pariatur commodo irure cillum amet proident culpa. Eu veniam cillum qui eiusmod anim cupidatat dolor consequat Lorem ad id ipsum id. Magna anim voluptate ex id aliquip tempor mollit anim aliqua eu aliquip velit ipsum. Et sint aliqua Lorem in sint veniam cillum incididunt.","grade":1,"distance":2.6,"lane_type":"Shared Lane","geojson":{"type":"Feature","properties":{"name":"Kirkham St"},"geometry":{"coordinates":[[-122.509231,37.758399],[-122.461681,37.760537]],"type":"LineString"},"id":"92ccf4aed36e5c0e67e5238cd4027d01","centroid":[-122.485456,37.759468]}},{"name":"Alemany Blvd","description":"Deserunt fugiat cillum tempor dolor sunt aliqua elit consectetur labore. Aliqua veniam ex et aute qui officia. Quis consequat aliqua do deserunt irure sit. Irure aliqua ut reprehenderit sint et quis. Aliqua do exercitation fugiat incididunt in ut aliqua culpa Lorem.","grade":7,"distance":2.29,"lane_type":"Sharrows","geojson":{"type":"Feature","properties":{"name":"Alemany Blvd"},"geometry":{"coordinates":[[-122.457132,37.709967],[-122.453999,37.710748],[-122.450308,37.713328],[-122.445545,37.715331],[-122.439622,37.720151],[-122.437434,37.723851],[-122.435588,37.727449],[-122.433485,37.729893],[-122.431211,37.730572],[-122.432112,37.73322]],"type":"LineString"},"id":"8e85250462fd834e1b9d4ccd35c25c50","centroid":[-122.44164360000002,37.721451]}},{"name":"7th Avenue/Laguna Honda Blvd","description":"Aliquip nostrud elit aute id. Aliqua tempor laboris ad est cillum ex duis. Mollit sunt laborum sunt proident est amet eu incididunt consequat culpa adipisicing labore commodo anim. Labore laboris nisi aliquip do et et excepteur ullamco eiusmod ipsum id sit occaecat. Consequat non aute fugiat quis ex pariatur esse Lorem consequat excepteur nisi.","grade":9,"distance":1.35,"lane_type":"Shared Lane","geojson":{"type":"Feature","properties":{"name":"7th Avenue/Laguna Honda Blvd","title":"7th Avenue/Laguna Honda Blvd","description":"","stroke":"#1087bf","stroke-width":4,"stroke-opacity":1,"marker-color":"","marker-size":"","marker-symbol":""},"geometry":{"coordinates":[[-122.464234,37.765965],[-122.463526,37.755311],[-122.463827,37.753852],[-122.463355,37.75297],[-122.462239,37.752003],[-122.461552,37.75146],[-122.461102,37.750883],[-122.460136,37.749373],[-122.459127,37.748474],[-122.458655,37.747728]],"type":"LineString"},"id":"8aeb753fc2e855b35ce7fa1aebc6b2c5","centroid":[-122.4617753,37.752801899999994]}},{"name":"Sanchez","description":"Minim ea labore irure cillum excepteur ex laboris incididunt duis dolore cillum. Enim veniam exercitation culpa fugiat voluptate occaecat sit reprehenderit velit minim. Eiusmod ex anim et occaecat esse proident sit reprehenderit voluptate dolor commodo proident. Labore culpa est quis cupidatat id proident ipsum consectetur reprehenderit do. Cupidatat occaecat non reprehenderit nostrud consequat esse magna adipisicing aute eiusmod.","grade":4,"distance":0.45,"lane_type":"Shared Lane","geojson":{"type":"Feature","properties":{"name":"Sanchez"},"geometry":{"coordinates":[[-122.43134,37.769306],[-122.430717,37.762742]],"type":"LineString"},"id":"8a5d2b45206cdcdaf1b216bdbac6c7b6","centroid":[-122.4310285,37.766024]}},{"name":"Columbus Avenue","description":"Anim irure laborum cillum minim. Amet anim eiusmod incididunt velit nostrud excepteur est veniam mollit consectetur. Proident anim mollit magna mollit amet elit officia ea in esse Lorem occaecat. Minim mollit laborum consectetur proident cupidatat Lorem. Aliquip amet ipsum et minim ipsum sint sint.","grade":4,"distance":1.18,"lane_type":"Sharrows","geojson":{"type":"Feature","properties":{"name":"Columbus Avenue"},"geometry":{"coordinates":[[-122.403295,37.795542],[-122.419538,37.806783]],"type":"LineString"},"id":"843474ebeac4a5f43f18a8a3d131f360","centroid":[-122.4114165,37.801162500000004]}},{"name":"Howard Street","description":"Ullamco pariatur consectetur et cupidatat dolore mollit sint velit deserunt quis sint mollit. Sint reprehenderit minim deserunt reprehenderit non cillum consectetur id. Aliqua id aliquip eiusmod magna aliquip laboris aliqua qui adipisicing nisi ad sit incididunt. Anim cupidatat est quis labore cupidatat occaecat nisi fugiat. Mollit eu non culpa irure incididunt aliqua sunt amet ut elit minim eiusmod aliquip voluptate.","grade":0,"distance":1.77,"lane_type":"Bike Path","geojson":{"type":"Feature","properties":{"name":"Howard Street"},"geometry":{"coordinates":[[-122.391386,37.792117],[-122.414474,37.774073]],"type":"LineString"},"id":"7aa13dbc8824799ae5fded68e51db269","centroid":[-122.40293,37.783095]}},{"name":"Steiner Street","description":"Occaecat velit fugiat fugiat anim ullamco occaecat dolore ea id ipsum. Incididunt proident ut nostrud veniam officia deserunt id duis quis tempor laborum. Nisi dolor id excepteur nostrud elit amet in commodo sit non ut nulla consectetur do. Nostrud ex amet voluptate magna minim irure cupidatat est dolore ad. Amet aute deserunt adipisicing culpa duis commodo tempor dolore laborum nostrud sunt do.","grade":5,"distance":1.49,"lane_type":"Bike Path","geojson":{"type":"Feature","properties":{"name":"Steiner Street"},"geometry":{"coordinates":[[-122.433228,37.777499],[-122.43752,37.79873]],"type":"LineString"},"id":"77a26f2440ad3e785aaa6b5efdcb47d9","centroid":[-122.435374,37.7881145]}},{"name":"Ocean  Avenue","description":"Deserunt est ea voluptate deserunt labore minim. Sint veniam qui et enim sunt officia deserunt ut fugiat non. Dolor incididunt tempor do ex nulla adipisicing dolor. Proident sit et cillum est elit magna laboris laboris mollit. Et ea mollit cupidatat dolor.","grade":4,"distance":3.3,"lane_type":"Sharrows","geojson":{"type":"Feature","properties":{"name":"Ocean  Avenue"},"geometry":{"coordinates":[[-122.49361,37.731862],[-122.475543,37.73271],[-122.468204,37.729384],[-122.467517,37.727687],[-122.465586,37.726363],[-122.461595,37.725039],[-122.451853,37.722935],[-122.444257,37.722867],[-122.437434,37.72375]],"type":"LineString"},"id":"744daa62d7e37bd42d69285a7bd28dbb","centroid":[-122.46284433333332,37.72695522222222]}},{"description":"Fugiat reprehenderit quis officia qui velit irure pariatur Lorem elit. Magna sit aliqua aute dolor. Aute fugiat occaecat quis eiusmod sit. Reprehenderit officia labore aliquip eu non dolor. Consequat fugiat minim dolor exercitation exercitation amet cillum fugiat commodo occaecat anim.","grade":4,"distance":0.9,"lane_type":"Separated Lane","geojson":{"type":"Feature","properties":{"title":"15th Avenue","description":"","stroke":"#1087bf","stroke-width":4,"stroke-opacity":1,"marker-color":"","marker-size":"","marker-symbol":""},"geometry":{"coordinates":[[-122.474577,37.787843],[-122.474405,37.786232],[-122.473568,37.774887]],"type":"LineString"},"id":"6efe4cc46716090ec31df24f889df992","centroid":[-122.47418333333333,37.78298733333333]}},{"name":"34th Avenue - Richmond","description":"In aliqua labore anim aliqua anim consectetur. Commodo duis sunt est exercitation eu nisi culpa incididunt officia cillum occaecat ea consectetur adipisicing. Irure deserunt incididunt aliquip ad fugiat ipsum consectetur ut esse dolore. Fugiat nisi duis quis do eiusmod. Excepteur amet irure ipsum commodo sunt duis minim eu officia aliquip aliqua et proident laborum.","grade":8,"distance":0.96,"lane_type":"Shared Lane","geojson":{"type":"Feature","properties":{"name":"34th Avenue - Richmond","title":"34th Avenue - Richmond","description":"","stroke":"#1087bf","stroke-width":4,"stroke-opacity":1,"marker-color":"","marker-size":"","marker-symbol":""},"geometry":{"coordinates":[[-122.500262,37.785469],[-122.497687,37.783231],[-122.494597,37.782145],[-122.493953,37.774039]],"type":"LineString"},"id":"686c0afcae311599055cbf175f960e41","centroid":[-122.49662475,37.781221]}},{"name":"Holloway Avenue","description":"Ad do nulla culpa adipisicing. Incididunt occaecat amet officia ullamco magna reprehenderit dolore proident esse. Nisi occaecat pariatur aliquip officia ullamco esse in veniam fugiat irure commodo dolor. Voluptate occaecat proident irure labore do ut do nostrud nisi non proident nulla. Eiusmod enim do reprehenderit irure cillum velit qui culpa sint esse.","grade":2,"distance":1.56,"lane_type":"Shared Lane","geojson":{"type":"Feature","properties":{"name":"Holloway Avenue"},"geometry":{"coordinates":[[-122.481229,37.721],[-122.476143,37.720813],[-122.472388,37.721645],[-122.46226,37.721679],[-122.46226,37.7219],[-122.453141,37.721849]],"type":"LineString"},"id":"67bc1ef5d13d6b25cbef43bfead2bf2c","centroid":[-122.46790349999999,37.721481]}},{"name":"The Wiggle","description":"Consequat labore proident eiusmod Lorem in. Laborum qui ad labore labore incididunt velit deserunt fugiat non veniam reprehenderit ullamco. Magna eu aute pariatur nulla exercitation dolore aliqua Lorem reprehenderit non. Quis ad mollit sint minim magna excepteur cupidatat deserunt ipsum in elit. Duis consectetur nisi magna deserunt anim dolore ad dolor pariatur.","grade":9,"distance":1.13,"lane_type":"Bike Path","geojson":{"type":"Feature","properties":{"name":"The Wiggle"},"geometry":{"coordinates":[[-122.426233,37.769595],[-122.429816,37.769366],[-122.429929,37.769412],[-122.431581,37.769311],[-122.431908,37.770969],[-122.43355,37.770757],[-122.433743,37.771694],[-122.435401,37.771482],[-122.435958,37.774285],[-122.440813,37.773661],[-122.440985,37.773581]],"type":"LineString"},"id":"67352d6bbd11c9cdc4e09f8d9d3b8292","centroid":[-122.4336288181818,37.771283000000004]}},{"name":"Lake Merced Blvd","description":"Aliqua et qui enim magna eiusmod consectetur culpa aliqua non sit officia Lorem occaecat. Voluptate dolor commodo ea culpa eu nostrud Lorem eu laborum laborum. Cillum ex laboris occaecat nostrud sunt proident adipisicing in dolore consectetur. Pariatur nostrud excepteur nulla cupidatat amet aute reprehenderit id tempor mollit. Ea esse esse aliqua nostrud ea.","grade":7,"distance":2.87,"lane_type":"Bike Path","geojson":{"type":"Feature","properties":{"name":"Lake Merced Blvd"},"geometry":{"coordinates":[[-122.484812,37.701546],[-122.485907,37.703244],[-122.485949,37.707539],[-122.48522,37.708863],[-122.485413,37.710459],[-122.485027,37.723919],[-122.483932,37.727144],[-122.485606,37.729282],[-122.489597,37.730318],[-122.49155,37.728926],[-122.493782,37.729588],[-122.496678,37.729079],[-122.498266,37.731336],[-122.499082,37.73154]],"type":"LineString"},"id":"5abd378c1f36aafa8e9c986d48daf06c","centroid":[-122.48934435714285,37.720913071428576]}},{"name":"Clay Street","description":"Sunt velit tempor ipsum pariatur consectetur mollit labore cupidatat. Ut incididunt ad eiusmod laboris ex tempor deserunt officia veniam qui veniam ipsum tempor tempor. Elit magna ut id ullamco fugiat aliqua aute ad. Incididunt est eiusmod magna reprehenderit. Id minim commodo quis ex eu id laboris occaecat est eu Lorem.","grade":7,"distance":1.59,"lane_type":"Shared Lane","geojson":{"type":"Feature","properties":{"name":"Clay Street"},"geometry":{"coordinates":[[-122.459363,37.789319],[-122.457432,37.789556],[-122.457325,37.788657],[-122.455673,37.788844],[-122.455394,37.787979],[-122.432541,37.790947]],"type":"LineString"},"id":"596f14524028b5879cb812e60074c18e","centroid":[-122.45295466666666,37.789217]}},{"name":"Illinois Street","description":"Ullamco incididunt fugiat aliqua consectetur sunt amet elit anim mollit officia fugiat ipsum do enim. Id irure consequat fugiat ea velit officia consectetur do velit laboris. Ea mollit amet elit ea irure in veniam tempor enim. Elit enim eiusmod deserunt aute qui aliqua. Dolore adipisicing non exercitation adipisicing aute ad laboris do qui laboris sit cupidatat voluptate.","grade":2,"distance":2.3,"lane_type":"Bike Path","geojson":{"type":"Feature","properties":{"name":"Illinois Street"},"geometry":{"coordinates":[[-122.389819,37.776244],[-122.387738,37.776294],[-122.387437,37.773326],[-122.385163,37.768645],[-122.386622,37.765643],[-122.387909,37.764421],[-122.386064,37.745709]],"type":"LineString"},"id":"4eb55d5fbec43b7eb1e0c7968d8e9c2b","centroid":[-122.3872502857143,37.76718314285714]}},{"name":"Ortega Street","description":"Adipisicing enim exercitation commodo ut commodo consequat proident. Amet id Lorem labore veniam sunt consequat deserunt aliqua culpa excepteur. Ut enim sunt occaecat sint. Excepteur magna aute id anim ut deserunt laboris sunt cupidatat ullamco tempor. Non adipisicing nostrud aute et.","grade":4,"distance":1.52,"lane_type":"Bike Path","geojson":{"type":"Feature","properties":{"name":"Ortega Street"},"geometry":{"coordinates":[[-122.499833,37.751375],[-122.472066,37.752631]],"type":"LineString"},"id":"4219c80cad9c46fdb94dbf8680ffcb3e","centroid":[-122.4859495,37.752003]}},{"name":"San Jose Ave","description":"Laboris dolore cupidatat reprehenderit magna quis magna veniam qui veniam sit ipsum eu tempor. Ex aliqua quis commodo consectetur laboris sit pariatur culpa aliquip. Ullamco nulla fugiat cillum fugiat laboris nisi est pariatur enim culpa consequat ut voluptate. Tempor labore labore occaecat exercitation duis exercitation laborum do irure esse duis sit in. Elit laboris aliquip exercitation sint sunt nisi aliqua reprehenderit cupidatat.","grade":6,"distance":1.38,"lane_type":"Sharrows","geojson":{"type":"Feature","properties":{"name":"San Jose Ave"},"geometry":{"coordinates":[[-122.434494,37.732133],[-122.427949,37.73529],[-122.425696,37.737157],[-122.424538,37.738514],[-122.424001,37.740584],[-122.422156,37.745335],[-122.422456,37.747965]],"type":"LineString"},"id":"40c858f11e8da2787cfc80464e427dd8","centroid":[-122.42589857142856,37.73956828571429]}},{"name":"Potrero","description":"Mollit nulla officia minim eiusmod voluptate. Consequat non ea quis officia excepteur sit nisi commodo commodo mollit. Non proident do duis consequat deserunt adipisicing sit anim laboris duis id. In proident reprehenderit in sunt est. Nisi ipsum laboris exercitation aliquip laboris aliqua quis sunt.","grade":7,"distance":1.4,"lane_type":"Shared Lane","geojson":{"type":"Feature","properties":{"name":"Potrero"},"geometry":{"coordinates":[[-122.407844,37.769272],[-122.406105,37.750968],[-122.405183,37.749136]],"type":"LineString"},"id":"3e46c6c8ce98b2fba3dfa0678223e7c3","centroid":[-122.40637733333331,37.75645866666667]}},{"name":"34th Avenue - Sunset","description":"Nostrud qui et ullamco dolore id occaecat minim. Esse sint enim commodo in laboris cupidatat anim reprehenderit nulla sunt non sint eu. Et ea magna enim ut nulla sit. Minim officia ut consectetur do cillum ex qui est ullamco eiusmod. Fugiat commodo occaecat occaecat officia occaecat fugiat.","grade":2,"distance":2.12,"lane_type":"Separated Lane","geojson":{"type":"Feature","properties":{"name":"34th Avenue - Sunset","title":"34th Avenue - Sunset","description":"","stroke":"#1087bf","stroke-width":4,"stroke-opacity":1,"marker-color":"","marker-size":"","marker-symbol":""},"geometry":{"coordinates":[[-122.493352,37.764608],[-122.491228,37.733983]],"type":"LineString"},"id":"3c9a39e773ea2e3bd80446086551f327","centroid":[-122.49229,37.7492955]}},{"name":"Vicente Street","description":"Aute commodo ad culpa cupidatat quis qui quis laborum exercitation. Veniam eu dolore est non eiusmod fugiat aute nisi ut. Officia fugiat fugiat velit duis deserunt aliqua. Ipsum Lorem nisi ea aliqua nostrud dolor ut. Officia proident officia eu magna ut.","grade":7,"distance":2.25,"lane_type":"Shared Lane","geojson":{"type":"Feature","properties":{"name":"Vicente Street"},"geometry":{"coordinates":[[-122.506742,37.738005],[-122.469835,37.739634],[-122.468376,37.740109],[-122.467045,37.739736],[-122.466101,37.739091]],"type":"LineString"},"id":"398d8e3ce840bbb47bbe890b2b4d1432","centroid":[-122.4756198,37.739315]}},{"name":"Caesar Chavez","description":"Adipisicing nulla culpa sit et enim. Qui quis elit esse eiusmod ex non cillum anim aliqua aliquip. Tempor consequat cillum ex sint minim aute do esse sint officia adipisicing consequat sint deserunt. Nostrud enim ex pariatur eiusmod veniam officia est est. Et adipisicing non consectetur culpa et ex excepteur dolore.","grade":1,"distance":1.97,"lane_type":"Dedicated Lane","geojson":{"type":"Feature","properties":{"name":"Caesar Chavez"},"geometry":{"coordinates":[[-122.422392,37.74805],[-122.407929,37.748372],[-122.406277,37.748932],[-122.404561,37.74917],[-122.403016,37.749543],[-122.402179,37.749373],[-122.392458,37.750069],[-122.3866,37.750358]],"type":"LineString"},"id":"2bf5a992d9b0174d48f28aef4e0a31d8","centroid":[-122.40317650000001,37.749233374999996]}},{"name":"Monterey Boulevard","description":"Occaecat do aute fugiat ad aliqua non est cupidatat dolor. Eu ullamco in irure proident. Et laboris elit proident minim ipsum laboris ut laboris tempor anim velit. Irure cupidatat pariatur aliqua officia nostrud aute labore nulla nisi fugiat. Adipisicing cupidatat nostrud incididunt Lorem.","grade":7,"distance":2.13,"lane_type":"Bike Path","geojson":{"type":"Feature","properties":{"name":"Monterey Boulevard"},"geometry":{"coordinates":[[-122.465972,37.739023],[-122.465758,37.737598],[-122.466316,37.736444],[-122.466058,37.733491],[-122.46387,37.731658],[-122.462968,37.73047],[-122.461681,37.729927],[-122.459664,37.730946],[-122.458162,37.730878],[-122.454342,37.731658],[-122.436747,37.73159]],"type":"LineString"},"id":"263dc9107ab2a62f53fe18de07006ee6","centroid":[-122.46013981818182,37.73306209090909]}},{"name":"Townsend Street","description":"Tempor velit est nisi excepteur voluptate fugiat. Esse Lorem officia dolore excepteur occaecat non dolore quis ullamco eu commodo nisi aute et. Amet incididunt nostrud velit Lorem commodo ullamco occaecat est culpa velit ex ad. Amet deserunt excepteur consequat commodo nisi nulla ex dolore officia in consectetur. Voluptate culpa culpa culpa laboris magna ex officia nulla et.","grade":5,"distance":1.19,"lane_type":"Shared Lane","geojson":{"type":"Feature","properties":{"name":"Townsend Street"},"geometry":{"coordinates":[[-122.403874,37.770104],[-122.389047,37.781789],[-122.388124,37.781806]],"type":"LineString"},"id":"263a13aaf80809bc386b87773bf81023","centroid":[-122.39368166666668,37.77789966666667]}},{"name":"20th Avenue","description":"Ad qui ut fugiat nostrud veniam ut tempor laborum sit elit ipsum mollit. Ut id incididunt magna magna non sunt aliqua laboris. Ex nisi proident exercitation adipisicing reprehenderit. Consectetur ad aliquip laborum ex cupidatat quis tempor cillum in eiusmod ea qui adipisicing consectetur. Deserunt eiusmod enim consectetur fugiat incididunt aute dolore in quis aliqua proident.","grade":6,"distance":2.61,"lane_type":"Dedicated Lane","geojson":{"type":"Feature","properties":{"name":"20th Avenue"},"geometry":{"coordinates":[[-122.478375,37.76566],[-122.476422,37.737462],[-122.477452,37.737377],[-122.477324,37.737021],[-122.476701,37.736817],[-122.476315,37.736104],[-122.475543,37.735986],[-122.4755,37.734747],[-122.476208,37.734662],[-122.475972,37.73008]],"type":"LineString"},"id":"22a315c82c049c69a34b2ddff6135775","centroid":[-122.47658119999998,37.73859159999999]}},{"name":"Mason Street","description":"Nulla magna amet pariatur irure adipisicing elit et proident cupidatat. Voluptate id nostrud nulla sint sunt qui officia nulla incididunt sit pariatur. Proident deserunt nostrud ipsum eiusmod in. Cillum aliqua dolor laborum sit cupidatat ipsum cillum culpa enim occaecat pariatur. Nisi velit velit commodo in cupidatat eiusmod.","grade":9,"distance":1.26,"lane_type":"Dedicated Lane","geojson":{"type":"Feature","properties":{"name":"Mason Street"},"geometry":{"coordinates":[[-122.448506,37.805037],[-122.459836,37.80346],[-122.460951,37.802866],[-122.467496,37.80368],[-122.468268,37.804833],[-122.468891,37.806257]],"type":"LineString"},"id":"1feaf16a002b71aeefea99d1ff1289f4","centroid":[-122.46232466666665,37.80435549999999]}},{"name":"The Embarcadero","description":"Occaecat ipsum incididunt duis aute. Veniam aute eu eiusmod eu veniam culpa amet nisi adipisicing velit sit. Reprehenderit est sunt laborum dolor id fugiat amet proident consequat cupidatat consectetur aliqua. Laboris reprehenderit id aliquip laborum Lorem. Ad quis occaecat eiusmod laborum do et id excepteur occaecat.","grade":8,"distance":2.71,"lane_type":"Dedicated Lane","geojson":{"type":"Feature","properties":{"name":"The Embarcadero"},"geometry":{"coordinates":[[-122.412478,37.808631],[-122.409034,37.808148],[-122.40705,37.807393],[-122.404475,37.806096],[-122.40176,37.804087],[-122.394014,37.795474],[-122.392287,37.793702],[-122.390881,37.792464],[-122.389154,37.791099],[-122.388306,37.789616],[-122.387802,37.788361],[-122.387716,37.786919],[-122.388033,37.781628],[-122.387754,37.781166],[-122.387609,37.779839],[-122.387512,37.778364]],"type":"LineString"},"id":"133236a1c211b4e8174451e71fa404ae","centroid":[-122.39474156250002,37.79331168750001]}},{"name":"The Panhandle","description":"Ad ea adipisicing consequat anim do commodo ipsum id. Deserunt duis amet amet enim et qui nulla ullamco nostrud non do enim velit. Veniam sunt et cillum duis veniam dolore et cillum ullamco velit. Amet et sint commodo non velit incididunt et nulla pariatur magna. Excepteur ex veniam tempor sit cupidatat eu aliquip aliqua do nulla nisi nulla irure.","grade":1,"distance":0.75,"lane_type":"Shared Lane","geojson":{"type":"Feature","properties":{"name":"The Panhandle"},"geometry":{"coordinates":[[-122.441028,37.773509],[-122.441419,37.773458],[-122.441664,37.773316],[-122.442026,37.773216],[-122.442911,37.773068],[-122.443313,37.773116],[-122.443737,37.77308],[-122.444171,37.773038],[-122.444568,37.772949],[-122.445032,37.772951],[-122.44584,37.772856],[-122.446172,37.772822],[-122.446483,37.77261],[-122.447074,37.772669],[-122.44769,37.772542],[-122.448374,37.772521],[-122.449257,37.772169],[-122.450743,37.772224],[-122.451306,37.772114],[-122.452307,37.77201],[-122.452486,37.772147],[-122.454171,37.771478]],"type":"LineString"},"id":"106593b46315bbd60d7905974f1cc98f","centroid":[-122.44644418181817,37.772721045454546]}},{"name":"3rd Stree","description":"Ullamco eu culpa non veniam ullamco aute. Aute ipsum enim laborum nisi irure veniam. Irure velit ullamco adipisicing eu consectetur amet sit aliquip dolore consectetur mollit anim id ex. Enim id esse ex dolor tempor ad proident minim elit magna proident occaecat sit veniam. Laboris tempor deserunt aute laborum labore ad laboris ad ad cupidatat magna aliquip consectetur aute.","grade":2,"distance":5.01,"lane_type":"Shared Lane","geojson":{"type":"Feature","properties":{"name":"3rd Stree"},"geometry":{"coordinates":[[-122.40323,37.787097],[-122.390356,37.776888],[-122.389969,37.776244],[-122.387115,37.745115],[-122.393209,37.727857],[-122.3966,37.7201]],"type":"LineString"},"id":"0b165355c199f2fe27f609ac804a25dc","centroid":[-122.39341316666668,37.755550166666666]}},{"name":"Cabrillo","description":"Elit id culpa aliqua occaecat velit. Culpa veniam consectetur laborum enim cupidatat commodo. Aute ipsum ipsum proident non amet dolore velit culpa. Pariatur sint est veniam adipisicing mollit. Est nisi laborum culpa ut non amet.","grade":2,"distance":2.82,"lane_type":"Sharrows","geojson":{"type":"Feature","properties":{"name":"Cabrillo"},"geometry":{"coordinates":[[-122.458484,37.775667],[-122.510068,37.773275]],"type":"LineString"},"id":"0a436e825060ec7c89cc494862522022","centroid":[-122.484276,37.774471]}},{"name":"Folsom Street","description":"Ullamco deserunt irure occaecat veniam nulla do. Ipsum labore magna nisi enim. Tempor velit laborum velit labore sint ullamco dolor sint. Magna fugiat ea cupidatat aute sunt sint irure officia aliqua occaecat sint ipsum. Ipsum enim eu veniam ipsum aliquip sint consectetur laboris non eiusmod tempor adipisicing.","grade":8,"distance":3.51,"lane_type":"Dedicated Lane","geojson":{"type":"Feature","properties":{"name":"Folsom Street"},"geometry":{"coordinates":[[-122.413648,37.74833],[-122.415622,37.768535],[-122.415611,37.7694],[-122.415418,37.770171],[-122.415,37.770892],[-122.414581,37.771418],[-122.412983,37.772758],[-122.390055,37.79093]],"type":"LineString"},"id":"06e97c69b7d31c8fbb31bec23fee55af","centroid":[-122.41161475,37.77030425]}},{"name":"23rd Ave","description":"Et minim incididunt amet enim ullamco reprehenderit veniam dolor ut. Ipsum ex fugiat eu labore occaecat non aliqua anim aliqua. Consectetur excepteur amet sit sit laborum culpa. Sint non non excepteur voluptate. Et magna minim aliqua pariatur qui.","grade":9,"distance":1.04,"lane_type":"Sharrows","geojson":{"type":"Feature","properties":{"name":"23rd Ave"},"geometry":{"coordinates":[[-122.482967,37.785809],[-122.482023,37.772648],[-122.480607,37.772699],[-122.480928,37.772003]],"type":"LineString"},"id":"062b154773a767c648d51c2dabe4ac5f","centroid":[-122.48163125,37.77578975]}},{"name":"Market Street","description":"Nisi culpa velit anim velit ad incididunt mollit. Lorem occaecat anim tempor culpa proident eu incididunt eu elit consequat sint ullamco. Ad eu ipsum consectetur commodo excepteur deserunt. Dolore veniam occaecat sint sint proident adipisicing sint. Anim quis quis consequat amet ad proident occaecat.","grade":8,"distance":3.18,"lane_type":"Shared Lane","geojson":{"type":"Feature","properties":{"name":"Market Street"},"geometry":{"coordinates":[[-122.39395,37.79522],[-122.394851,37.794452],[-122.419302,37.775192],[-122.429666,37.766915],[-122.435224,37.762742]],"type":"LineString"},"id":"03d42e45e03ede069583513b4e5e4edd","centroid":[-122.4145986,37.7789042]}}]